pytest_ebics_sandbox/__init__.py
pytest_ebics_sandbox-0.1.2.dist-info/entry_points.txt
pytest_ebics_sandbox-0.1.2.dist-info/LICENSE
pytest_ebics_sandbox-0.1.2.dist-info/WHEEL
pytest_ebics_sandbox-0.1.2.dist-info/METADATA
pytest_ebics_sandbox-0.1.2.dist-info/RECORD
